skiptests/__init__.py
django_skiptest-1.0.0.dist-info/LICENSE
django_skiptest-1.0.0.dist-info/METADATA
django_skiptest-1.0.0.dist-info/WHEEL
django_skiptest-1.0.0.dist-info/top_level.txt
django_skiptest-1.0.0.dist-info/RECORD
